README
pyreplace
pyreplace.py
setup.py
pyreplace.egg-info/PKG-INFO
pyreplace.egg-info/SOURCES.txt
pyreplace.egg-info/dependency_links.txt
pyreplace.egg-info/top_level.txt