Metadata-Version: 1.0
Name: pyreplace
Version: 1.0
Summary: Recursively find and replace in file names and contents.
Home-page: http://www.pynguins.com
Author: Richie Ward
Author-email: RichieS@GMail.com
License: BSD
Keywords: rename file tool command find replace
Platform: UNKNOWN
Classifier: Development Status :: 6 - Mature
Classifier: Topic :: Utilities
Classifier: Topic :: Text Processing :: General
Classifier: License :: OSI Approved :: BSD License
